CONTRIBUTING.rst
HISTORY.rst
LICENSE
MANIFEST.in
README.rst
pip-requirements.txt
pyproject.toml
requirements_dev.txt
setup.cfg
setup.py
docs/API.rst
docs/Makefile
docs/conf.py
docs/contributing.rst
docs/history.rst
docs/index.rst
docs/installation.rst
docs/issues.rst
docs/make.bat
docs/method.rst
docs/modules.rst
docs/performance.rst
docs/readme.rst
docs/reference.rst
docs/ultranest.rst
docs/static/recursion.jpg
examples/populationstepsampler6.pyx
examples/populationstepsampler7.pyx
tests/benchmark_maxradius.py
tests/clusters2.txt
tests/clusters2_radius.txt
tests/eggboxpoints.tsv
tests/eggboxregion.txt
tests/overclustered_20.npz
tests/overclustered_23.npz
tests/overclustered_24.npz
tests/overclustered_27.npz
tests/overclustered_42.npz
tests/overclustered_u.txt
tests/overclustered_u_20.txt
tests/overclustered_u_23.txt
tests/overclustered_u_24.txt
tests/overclustered_u_27.txt
tests/overclustered_u_49.txt
tests/test_calibrator.py
tests/test_clustering.py
tests/test_flatnuts.py
tests/test_hotstart.py
tests/test_netiterintegrate.py
tests/test_ordertest.py
tests/test_plot.py
tests/test_popstepsampling.py
tests/test_regionsampling.py
tests/test_run.py
tests/test_samplingpath.py
tests/test_stepsampling.py
tests/test_store.py
tests/test_transforms.py
tests/test_utils.py
tests/test_viz.py
ultranest/__init__.py
ultranest/calibrator.py
ultranest/dychmc.py
ultranest/dyhmc.py
ultranest/flatnuts.py
ultranest/hotstart.py
ultranest/integrator.py
ultranest/mlfriends.pyx
ultranest/netiter.py
ultranest/ordertest.py
ultranest/pathsampler.py
ultranest/plot.py
ultranest/popstepsampler.py
ultranest/samplingpath.py
ultranest/solvecompat.py
ultranest/stepfuncs.pyx
ultranest/stepsampler.py
ultranest/store.py
ultranest/utils.py
ultranest/viz.py
ultranest.egg-info/PKG-INFO
ultranest.egg-info/SOURCES.txt
ultranest.egg-info/dependency_links.txt
ultranest.egg-info/not-zip-safe
ultranest.egg-info/requires.txt
ultranest.egg-info/top_level.txt