Metadata-Version: 2.2
Name: ultranest
Version: 4.5.0
Summary: Fit and compare complex models reliably and rapidly. Advanced Nested Sampling.
Home-page: https://github.com/JohannesBuchner/ultranest
Author: Johannes Buchner
Author-email: johannes.buchner.acad@gmx.com
License: GNU General Public License v3
Keywords: ultranest
Classifier: Development Status :: 5 - Production/Stable
Classifier: Intended Audience :: Science/Research
Classifier: Intended Audience :: Developers
Classifier: License :: OSI Approved :: GNU General Public License v3 (GPLv3)
Classifier: Natural Language :: English
Classifier: Programming Language :: Python :: 2
Classifier: Programming Language :: Python :: 2.7
Classifier: Programming Language :: Python :: 3
Classifier: Programming Language :: Python :: 3.5
Classifier: Programming Language :: Python :: 3.6
Classifier: Programming Language :: Python :: 3.7
Requires-Python: >=2.7, !=3.0.*, !=3.1.*, !=3.2.*, !=3.3.*, !=3.4.*
License-File: LICENSE
Requires-Dist: numpy
Requires-Dist: cython
Requires-Dist: matplotlib
Requires-Dist: corner
Dynamic: author
Dynamic: author-email
Dynamic: classifier
Dynamic: description
Dynamic: home-page
Dynamic: keywords
Dynamic: license
Dynamic: requires-dist
Dynamic: requires-python
Dynamic: summary
